omeganlp/__init__.py
omeganlp/core/__init__.py
omeganlp/core/callbacks.py
omeganlp/core/io.py
omeganlp/core/optim.py
omeganlp/core/processing.py
omeganlp/core/vocabulary.py
omeganlp/core/mixins/__init__.py
omeganlp/core/mixins/hparam_mixin.py
omeganlp/data/__init__.py
omeganlp/data/processor/__init__.py
omeganlp/data/processor/mrc.py
omeganlp/data/processor/sequenceclassification.py
omeganlp/litmodel/__init__.py
omeganlp/litmodel/sequenceclassification.py
omeganlp/model/__init__.py
omeganlp/model/bert_classification.py
omeganlp/model/bert_crf.py
omeganlp/model/bertem.py
omeganlp/model/bertflow.py
omeganlp/model/bertwhitning.py
omeganlp/model/setencebert.py
omeganlp/model/simcse.py
omeganlp/model/textcnn.py
omeganlp/model/textrcnn.py
omeganlp/model/textrnn.py
omeganlp/task/__init__.py
omeganlp-0.0.2.dist-info/LICENSE
omeganlp-0.0.2.dist-info/METADATA
omeganlp-0.0.2.dist-info/WHEEL
omeganlp-0.0.2.dist-info/top_level.txt
omeganlp-0.0.2.dist-info/RECORD
